exodus_helper/__init__.py
exodus_helper/core.py
exodus_helper/dir_exodus.py
exodus_helper/element_calculations.py
exodus_helper/reconfigure_mesh.py
exodus_helper/render_mesh.py
exodus_helper/topology.py
exodus_helper-1.5.6.dist-info/METADATA
exodus_helper-1.5.6.dist-info/WHEEL
exodus_helper-1.5.6.dist-info/RECORD
