Metadata-Version: 2.1
Name: exodus_helper
Version: 1.5.6
Summary: A package for manipulating ExodusII databases
Home-page: https://github.com/sandialabs/exodus_helper
License: BSD-3-Clause
Keywords: finite element,ExodusII
Author: Coleman Alleman
Author-email: callema@sandia.gov
Maintainer: Coleman Alleman
Maintainer-email: callema@sandia.gov
Requires-Python: >=3.11,<3.13
Classifier: License :: OSI Approved :: BSD License
Classifier: Programming Language :: Python :: 3
Classifier: Programming Language :: Python :: 3.11
Classifier: Programming Language :: Python :: 3.12
Classifier: Topic :: Software Development :: Libraries :: Python Modules
Provides-Extra: all
Provides-Extra: dev
Provides-Extra: docs
Provides-Extra: testing
Requires-Dist: GitPython ; extra == "testing" or extra == "all"
Requires-Dist: docstr-coverage ; extra == "docs" or extra == "all"
Requires-Dist: nbsphinx ; extra == "docs" or extra == "all"
Requires-Dist: netCDF4 (>=1,<2)
Requires-Dist: numpy (>=2,<3)
Requires-Dist: packaging (>=24,<25)
Requires-Dist: pytest ; extra == "testing" or extra == "all"
Requires-Dist: pytest-cov ; extra == "testing" or extra == "all"
Requires-Dist: scipy (>=1,<2)
Requires-Dist: sphinx ; extra == "docs" or extra == "all"
Requires-Dist: sphinx_rtd_theme ; extra == "docs" or extra == "all"
Project-URL: Documentation, https://github.com/sandialabs/exodus_helper
Project-URL: Repository, https://github.com/sandialabs/exodus_helper
